CHANGES.rst
COPYING
MANIFEST.in
README.rst
bootstrap.py
buildout.cfg
setup.py
doc/Makefile
doc/branding.rst
doc/conf.py
doc/configuration.rst
doc/domains.rst
doc/entities.rst
doc/index.rst
doc/install.rst
doc/moderation_flow.rst
doc/remote-auth.rst
doc/upgrade.rst
doc/users.rst
peer/__init__.py
peer/local_settings.py
peer/metadata_import_terms_of_use.txt
peer/peer.wsgi
peer/settings.py
peer/urls.py
peer/user_register_terms_of_use.txt
peer.egg-info/PKG-INFO
peer.egg-info/SOURCES.txt
peer.egg-info/dependency_links.txt
peer.egg-info/not-zip-safe
peer.egg-info/requires.txt
peer.egg-info/top_level.txt
peer/account/__init__.py
peer/account/forms.py
peer/account/models.py
peer/account/urls.py
peer/account/views.py
peer/account/templates/account/edit.html
peer/account/templates/account/invitation_email.txt
peer/account/templates/account/invite_friend.html
peer/account/templates/account/list_superusers.html
peer/account/templates/account/manage_admin_team.html
peer/account/templates/account/menu.html
peer/account/templates/account/profile.html
peer/account/templatetags/__init__.py
peer/account/templatetags/account.py
peer/account/templatetags/session.py
peer/customfields/__init__.py
peer/domain/__init__.py
peer/domain/admin.py
peer/domain/forms.py
peer/domain/models.py
peer/domain/tests.py
peer/domain/urls.py
peer/domain/utils.py
peer/domain/validation.py
peer/domain/views.py
peer/domain/migrations/0001_initial.py
peer/domain/migrations/0002_auto_20150624_0859.py
peer/domain/migrations/__init__.py
peer/domain/templates/domain/add.html
peer/domain/templates/domain/force_ownership.html
peer/domain/templates/domain/list_delegates.html
peer/domain/templates/domain/notify_domain_activity.html
peer/domain/templates/domain/notify_domain_activity.txt
peer/domain/templates/domain/remove.html
peer/domain/templates/domain/sharing.html
peer/domain/templates/domain/validation_by_mail.html
peer/domain/templates/domain/validation_by_mail.txt
peer/domain/templates/domain/verification_button.html
peer/domain/templates/domain/verify.html
peer/domain/templatetags/__init__.py
peer/domain/templatetags/verification_tags.py
peer/entity/__init__.py
