Metadata-Version: 1.1
Name: peer
Version: 0.25.0
Summary: Public Endpoint Entities Registry
Home-page: https://github.com/Yaco-Sistemas/peer
Author: Terena
Author-email: UNKNOWN
License: BSD
Platform: UNKNOWN
Classifier: Development Status :: 4 - Beta
Classifier: Environment :: Web Environment
Classifier: Framework :: Django
Classifier: License :: OSI Approved :: BSD License
Classifier: Operating System :: OS Independent
Classifier: Programming Language :: Python
